{
    "name": "kaleido-network",
    "version": "1.0.0",
    "client": {
        "organization": "TS",
        "connection": {
            "timeout": {
                "peer": {
                    "endorser": "300"
                }
            }
        }
    },
    "organizations": {
        "u1hpn7jii5": {
            "mspid": "u1hpn7jii5",
            "peers": [
                "LabNode"
            ],
            "certificateAuthorities": [
                "TS-CA"
            ]
        }
    },
    "peers": {
        "LabNode": {
            "url": "grpcs://u1upeehyfy-u1mxrqwcyw-peer.us1-azure-ws.kaleido.io:30641",
            "tlsCACerts": {
                "path": "./blockchain/network/connection-profiles/cert.pem"
            },
            "grpcOptions": {
                "ssl-target-name-override": "u1upeehyfy-u1mxrqwcyw-peer.us1-azure-ws.kaleido.io"
            }
        }
    },
    "certificateAuthorities": {
        "TS-CA": {
            "url": "https://u1upeehyfy-u1hpn7jii5-ca.us1-azure-ws.kaleido.io:30641",
            "caName": "TS CA",
            "tlsCACerts": {
                "path": "./blockchain/network/connection-profiles/cert.pem"
            },
            "httpOptions": {
                "verify": false
            }
        }
    }
}
